flask_kafka/__init__.py
flask_kafka/consumer.py
flask_kafka/flask_kafka.py
flask_kafka/producer.py
flask_kafka_python-0.0.2.dist-info/LICENSE
flask_kafka_python-0.0.2.dist-info/METADATA
flask_kafka_python-0.0.2.dist-info/WHEEL
flask_kafka_python-0.0.2.dist-info/top_level.txt
flask_kafka_python-0.0.2.dist-info/RECORD
