Metadata-Version: 2.1
Name: flask-kafka-python
Version: 0.0.2
Summary: Make it easier to integrate flask with kafka
Home-page: https://github.com/cookieGeGe/flask-kafka-python
Author: cookieGeGe
Author-email: nimzy.maina@gmail.com
License: MIT
Keywords: kafka,consumer,kafkaesque,flask,simple,consumer,flask style,decorator
Platform: any
Requires-Python: >=3.6
License-File: LICENSE
Requires-Dist: kafka-python
